obsidianhtml_md_mermaid_fork.py
obsidianhtml_md_mermaid_fork-0.1.5.dist-info/LICENSE
obsidianhtml_md_mermaid_fork-0.1.5.dist-info/METADATA
obsidianhtml_md_mermaid_fork-0.1.5.dist-info/WHEEL
obsidianhtml_md_mermaid_fork-0.1.5.dist-info/top_level.txt
obsidianhtml_md_mermaid_fork-0.1.5.dist-info/RECORD
