Metadata-Version: 2.1
Name: obsidianhtml-md-mermaid-fork
Version: 0.1.5
Summary: Bugfix special characters of md_mermaid, because the dev doesn't want to fix the bug.
Home-page: https://github.com/obsidian-html/md_mermaid
Author: https://github.com/dwrolvink
Author-email: dwrolvink@protonmail.com
License: UNKNOWN
Platform: UNKNOWN
Classifier: Development Status :: 4 - Beta
Classifier: Operating System :: OS Independent
Classifier: License :: OSI Approved :: GNU General Public License v3 (GPLv3)
Classifier: Intended Audience :: Developers
Classifier: Programming Language :: Python
Classifier: Topic :: Text Processing :: Filters
Classifier: Topic :: Text Processing :: Markup :: HTML
License-File: LICENSE
Requires-Dist: markdown (>=2.5)
